omar.py
backend.cpython-312-x86_64-linux-gnu.so
omar.libs/libblas-357956a1.so.3.4.2
omar.libs/libquadmath-96973f99.so.0.0.0
omar.libs/libgfortran-91cc3cb1.so.3.0.0
omar.libs/libgfortran-040039e1.so.5.0.0
omar.libs/liblapack-1ad85175.so.3.4.2
omar-1.0.dist-info/WHEEL
omar-1.0.dist-info/LICENSE.txt
omar-1.0.dist-info/METADATA
omar-1.0.dist-info/RECORD
