Metadata-Version: 2.1
Name: omar
Version: 1.0
Summary: Open Multivariate Adaptive Regression
Author-Email: Tim Walter <tim.walter@tum.de>
License: Copyright (c) 2018 The Python Packaging Authority
Classifier: Programming Language :: Python :: 3
Classifier: Programming Language :: Python :: 3.12
Classifier: Programming Language :: Python :: 3.13
Classifier: Programming Language :: Python :: 3 :: Only
Classifier: License :: OSI Approved :: MIT License
Classifier: Operating System :: OS Independent
Classifier: Intended Audience :: Science/Research
Classifier: Intended Audience :: Developers
Classifier: Topic :: Software Development
Classifier: Topic :: Scientific/Engineering
Classifier: Typing :: Typed
Classifier: Operating System :: Microsoft :: Windows
Classifier: Operating System :: Unix
Classifier: Operating System :: MacOS
Project-URL: Homepage, https://github.com/Helge-Stein-Group/omar
Project-URL: Issues, https://github.com/Helge-Stein-Group/omar/issues
Requires-Python: >=3.12
Requires-Dist: meson-python>=0.18.0
Requires-Dist: numpy>=2.2.6
Requires-Dist: scipy>=1.15.3
Requires-Dist: llvmlite>=0.46.0.dev0; python_version == "3.14"
Requires-Dist: llvmlite>=0.45.1; python_version < "3.14"
Requires-Dist: numba==0.63.0rc1; python_version == "3.14"
Requires-Dist: numba>=0.61.2; python_version < "3.14"
Requires-Dist: jaxtyping>=0.3.2
Requires-Dist: beartype>=0.21.0
Requires-Dist: matplotlib>=3.10.3
Requires-Dist: scipy>=1.15.3
Requires-Dist: ninja>=1.11.1.4
Requires-Dist: pytest>=8.4.0
